README.txt
setup.py
stompest/__init__.py
stompest.egg-info/PKG-INFO
stompest.egg-info/SOURCES.txt
stompest.egg-info/dependency_links.txt
stompest.egg-info/namespace_packages.txt
stompest.egg-info/requires.txt
stompest.egg-info/top_level.txt
stompest.egg-info/zip-safe
stompest/_backwards/__init__.py
stompest/config/__init__.py
stompest/error/__init__.py
stompest/protocol/__init__.py
stompest/protocol/commands.py
stompest/protocol/failover.py
stompest/protocol/frame.py
stompest/protocol/parser.py
stompest/protocol/session.py
stompest/protocol/spec.py
stompest/protocol/util.py
stompest/sync/__init__.py
stompest/sync/client.py
stompest/sync/transport.py
stompest/sync/examples/__init__.py
stompest/sync/examples/consumer.py
stompest/sync/examples/producer.py
stompest/sync/examples/ssl_consumer.py
stompest/tests/__init__.py
stompest/tests/commands_test.py
stompest/tests/failover_test.py
stompest/tests/frame_test.py
stompest/tests/parser_profile.py
stompest/tests/parser_test.py
stompest/tests/session_test.py
stompest/tests/sync_client_integration_test.py
stompest/tests/sync_client_test.py
stompest/tests/transport_test.py
stompest/tests/util_test.py
stompest/util/__init__.py