Metadata-Version: 1.1
Name: stompest
Version: 2.3.0
Summary: STOMP library for Python including a synchronous client.
Home-page: https://github.com/nikipore/stompest
Author: Jan Müller
Author-email: nikipore@gmail.com
License: Apache License 2.0
Keywords: stomp activemq rabbitmq apollo
Platform: UNKNOWN
Classifier: Development Status :: 5 - Production/Stable
Classifier: Topic :: System :: Networking
Classifier: Operating System :: OS Independent
Classifier: License :: OSI Approved :: Apache Software License
Classifier: Intended Audience :: Developers
Classifier: Programming Language :: Python :: 2.7
Classifier: Programming Language :: Python :: 3
Classifier: Topic :: Software Development :: Libraries :: Python Modules
